{
    "name": "Saitama Inu",
    "website": "https://saitama.digital",
    "description": "Welcome to Saitama, a community driven platform promoting financial well-being by empowering people of all ages and cultures to be in control of their money and create their own wealth opportunities.",
    "explorer": "https://bscscan.com/token/0x7919f52d0c820be87ab62459508808d29becf395",
    "type": "BEP20",
    "symbol": "SAITAMA",
    "decimals": 18,
    "status": "active",
    "id": "0x7919f52d0c820be87ab62459508808d29becf395"
}